Workbook

Sheet Lookup
A1: Template LEGACY cases S62A | B1: Field | C1: Data model | D1: Pre-application - DONE | E1: Application (Major) | F1: Application (Non Major) | G1: Notes S/S | H1: Horizon | I1: Notes Horizon
B2: Case reference | C2: Case reference | D2: Ref | E2: Ref | F2: Ref | H2: basic_data.CaseReference
A3: Case progress | B3: Pre-application status | C3: Status | D3: N/A | E3: N/A | F3: N/A | H3: N/A | I3: Manually override, will be Decision for most Horizon | J3: Should this be closed? -> yes
B4: Application Status | C4: Status | D4: N/A | E4: N/A | F4: N/A | H4: basic_data.Status
B5: Stage | C5: Stage | D5: N/A | E5: N/A | F5: N/A | H5: N/A | I5: Manually override, will be Decision for most Horizon
A6: Case type | B6: Application phase | C6: Application phase | D6: Set to be "Pre-application" | E6: Set to be "Application" | F6: Set to be "Application" | H6: case_reference_list.caseCategory | I6: if case_reference_list.caseCategory = "pre-app" then "pre-application", else "application"
B7: Application classification | C7: Application classification | D7: N/A | E7: Set to be "Major" | F7: Set to be "Non-major" | H7: N/A | I7: N/A - take from S/S
B8: Application type | C8: Application type | D8: Type of application | E8: Type of application | F8: Type of application | H8: basic_data.PermissionSought | I8: Manually check and remapp after
B9: Application subtype | C9: Application subtype | D9: N/A | E9: N/A | F9: N/A | G9: Planning Permission, Listed Building | H9: case_reference_list.caseCategory | I9: if case_reference_list.caseCategory = "listed-building" then "Listed building consent", else "Planning permission"
A10: Dates | B10: Notification received date | C10: Notification received date | D10: Pre-notification date | E10: Pre-notification date | F10: Pre-notification date | H10: N/A | I10: N/A - take from S/S
B11: Expected submission date | C11: Expected application submission date | D11: Expected submission date | E11: Expected submission date (not before) | F11: Expected submission date (not before) | H11: N/A | I11: N/A - take from S/S
B12: Pre-app/Application received date | C12: Pre-app/Application received date | D12: Receipt date | E12: Receipt date | F12: Receipt date | H12: key_dates.DateReceived
B13: Application acknowledged | C13: Application acknowledged | D13: N/A | E13: Letter 7 sent to applicant | F13: Letter 7 sent to applicant | H13: N/A | I13: N/A - take from S/S
B14: Further info requested | C14: Further information requested | D14: N/A | E14: Letter 8 sent to applicant - invalid (if applicable) | F14: Letter 8 sent to applicant - invalid (if applicable) | H14: N/A | I14: N/A - take from S/S
B15: Date agreed for additional info | C15: Date agreed for additional information | D15: N/A | E15: Date agreed for submission of additional docs | F15: Date agreed for submission of additional docs | H15: N/A | I15: N/A - take from S/S
B16: Application valid | C16: Application valid date | D16: N/A | E16: Valid Date | F16: Valid / Validation Date | H16: key_dates.DateValid
B17: Valid letters sent | C17: Valid letters sent | D17: N/A | E17: Valid letters (17 & 9) to LPA and Applicant | F17: Valid letters (17 & 9) to LPA and Applicant | H17: key_dates.ConsultationsWithRelevantAuthoritiesDate
B18: LPA questionnaire sent | C18: LPA questionnaire sent date | D18: N/A | E18: Letter 16 and Q sent to LPA | F18: Letter 16 and Q sent to LPA | H18: key_dates.DateInfoSentToLPA
B19: LPA questionnaire rec'd date | C19: LPA questionnaire received date | D19: N/A | E19: LPA Q received | F19: LPA Q received | G19: Check | H19: key_dates.DateInfoReturnedFromLPA
B20: Target publish date | C20: Target publish date | D20: N/A | E20: Application published due date (valid + 5 working days) | F20: Application published due date (valid + 5 working days) | H20: N/A | I20: N/A - take from S/S
B21: Publish date | C21: Publish date | D21: N/A | E21: Application documents published actual date | F21: Application documents published actual date | H21: key_dates.PublicityForApplicationsDate
B22: Press notice date | C22: Press notice date | D22: N/A | E22: PINS Interested parties press notice placed and TMP ref | F22: PINS Interested parties press notice placed and TMP ref | G22: Extract date | H22: key_dates.NewspaperAdvertDate
B23: Neighbours notified by LPA date | C23: Neighbours notified by LPA date | D23: N/A | E23: LPA Interested parties notification date | F23: LPA Interested parties notification date | H23: key_dates.DateNeighboursNotified
B24: LPA interested parties deadline | C24: LPA interested parties deadline | D24: N/A | E24: LPA Interested parties deadline | F24: LPA Interested parties deadline | H24: N/A | I24: N/A - take from S/S
B25: Site notice by LPA date | C25: Site notice by LPA date | D25: N/A | E25: N/A | F25: N/A | G25: Check | H25: key_dates.SiteNoticeDate
B26: Interested parties press notice deadline | C26: Interested parties press notice deadline | D26: N/A | E26: PINS interested parties press notice deadline | F26: PINS interested parties press notice deadline | H26: N/A | I26: N/A - take from S/S
B27: Mineral Applications date | C27: Mineral Applications | D27: N/A | E27: N/A | F27: N/A | G27: Check | H27: key_dates.MineralNotificationDate
B28: Interim findings date | C28: Interim findings date | D28: N/A | E28: Inspectors Interim findings (letter 25 to applicant) | F28: Inspectors Interim findings (letter 25 to applicant) | H28: N/A | I28: N/A - take from S/S
B29: Representations period - start | C29: Representations period | D29: N/A | E29: Consultations sent | F29: Consultations sent | H29: key_dates.RepresentationPeriodOpen
B30: Representations period - End | C30: Representations period | D30: N/A | E30: Consultations deadline (see Statutory Consultees and Town Parish Council list for list of parties consulted) | F30: Consultations deadline (see Statutory Consultees and Town Parish Council list for list of parties consulted) | H30: key_dates.RepresentationPeriodClose
B31: Reconsultation details sent date | C31: Reconsultation details | D31: N/A | E31: Reconsultation details | F31: Reconsultation details | G31: Extract sent date | H31: N/A | I31: N/A - take from S/S
B32: Reconsultation details deadline date | C32: Reconsultation details | D32: N/A | E32: Reconsultation details | F32: Reconsultation details | G32: Extract deadline date | H32: N/A | I32: N/A - take from S/S
B33: Representations publish date | C33: Representations publish date | D33: N/A | E33: Representations, LPA Questionnaire published date and procedure decision (within 5 days of close of comment period) | F33: Representations, LPA Questionnaire published date and procedure decision (within 5 days of close of comment period) | H33: key_dates.RepresentationsPublishedDate
B34: S106 submitted date | C34: S106 submitted date | D34: N/A | E34: S106 submitted date | F34: S106 submitted date | H34: N/A | I34: N/A - take from S/S
B35: Target decision date | C35: Target decision date | D35: N/A | E35: Target decision date (13 or 16 weeks from valid) | F35: Target decision date (8 weeks from valid) | H35: key_dates.TargetDecisionDate
B36: Extended target decision date | C36: Extended target decision date | D36: N/A | E36: N/A | F36: N/A | H36: key_dates.EoTTargetDate
B37: Recovered date | C37: Recovered date | D37: N/A | E37: N/A | F37: N/A | H37: N/A | I37: Never happened
B38: Site visit type | C38: Site visit type | D38: Site Visit | E38: Inspector USV or ARSV date (if needed) | F38: Inspector USV or ARSV date (if needed) | G38: Extract type | H38: N/A | I38: N/A - take from S/S
B39: Site visit date | C39: Site visit | D39: Site Visit | E39: Inspector USV or ARSV date (if needed) | F39: Inspector USV or ARSV date (if needed) | G39: Extract date | H39: N/A | I39: N/A - take from S/S
A40: Closed status dates | B40: Withdrawn date | C40: Withdrawn date | D40: N/A | E40: N/A | F40: N/A | G40: Process after | H40: N/A | I40: Process after
B41: Turned away date | C41: Turned away date | D41: N/A | E41: N/A | F41: N/A | G41: Process after | H41: N/A | I41: Process after
A42: Pre-application details | B42: Pre-application advice requested | C42: Pre-application advice | D42: N/A | E42: Pre-application advice? | F42: Pre-application advice? | G42: Process after | H42: basic_data.PreApplicationAdviceGiven
B43: Pre-app received date | C43: Pre-application received date | D43: Receipt date | E43: N/A | F43: N/A | G43: Do this after for Major/Non-major as will have to be the receipt date of the pre-app that is linked to case | H43: N/A | I43: N/A - take from S/S
B44: Pre-app reference | C44: Pre-application reference | D44: Ref | E44: Pre-application reference | F44: Pre-application reference | H44: N/A | I44: N/A - take from S/S
A45: LPA | B45: LPA | C45: LPA contact | D45: LPA | E45: LPA | F45: LPA | H45: basic_data.LPAName
B46: LPA contact - First name | C46: LPA contact | D46: N/A | E46: N/A | F46: N/A | H46: case_involvement.OrganisationName | I46: WHERE case_involvement.TypeOfInvolvement = "LPA" | J46: case_involvement.FirstName
B47: LPA contact - Last name | C47: LPA contact | D47: N/A | E47: N/A | F47: N/A | H47: N/A | J47: case_involvement.LastName
B48: LPA contact - Phone number | C48: LPA contact | D48: N/A | E48: N/A | F48: N/A | H48: case_involvement.TelephoneNumber | I48: WHERE case_involvement.TypeOfInvolvement = "LPA" | J48: try case_involvement.TelephoneOffice; else case_involvement.TelephoneMobile
B49: LPA contact - Email | C49: LPA contact | D49: N/A | E49: N/A | F49: N/A | H49: case_involvement.Email | I49: WHERE case_involvement.TypeOfInvolvement = "LPA" | J49: case_involvement.Email
A50: Secondary LPA | B50: Secondary LPA | C50: Secondary LPA contact | D50: N/A | E50: N/A | F50: N/A | H50: N/A | I50: There's only one for each case
B51: Secondary LPA - First name | C51: Secondary LPA contact | D51: N/A | E51: N/A | F51: N/A | H51: N/A | I51: There's only one for each case
B52: Secondary LPA - Last name | C52: Secondary LPA contact | D52: N/A | E52: N/A | F52: N/A | H52: N/A | I52: There's only one for each case
B53: Secondary LPA - Phone number | C53: Secondary LPA contact | D53: N/A | E53: N/A | F53: N/A | H53: N/A | I53: There's only one for each case
B54: Secondary LPA - Email | C54: Secondary LPA contact | D54: N/A | E54: N/A | F54: N/A | H54: N/A | I54: There's only one for each case
A55: Agent | B55: Agent organisation name | C55: Agent organisation name | D55: Agent | E55: Agent | F55: Agent | H55: case_involvement.OrganisationName | I55: WHERE case_involvement.TypeOfInvolvement = "Agent" , append to array
B56: Agent address 1 | C56: Agent address | D56: N/A | E56: N/A | F56: N/A | G56: Pull out from Agent after | H56: case_involvement.Address1 | I56: WHERE case_involvement.TypeOfInvolvement = "Agent" , append to array
B57: Agent address 2 | C57: Agent address | D57: N/A | E57: N/A | F57: N/A | G57: Pull out from Agent after | H57: case_involvement.Address2 | I57: WHERE case_involvement.TypeOfInvolvement = "Agent" , append to array
B58: Agent town or city | C58: Agent address | D58: N/A | E58: N/A | F58: N/A | G58: Pull out from Agent after | H58: case_involvement.City | I58: WHERE case_involvement.TypeOfInvolvement = "Agent" , append to array
B59: Agent county | C59: Agent address | D59: N/A | E59: N/A | F59: N/A | G59: Pull out from Agent after | H59: case_involvement.County | I59: WHERE case_involvement.TypeOfInvolvement = "Agent" , append to array
B60: Agent postcode | C60: Agent address | D60: N/A | E60: N/A | F60: N/A | G60: Pull out from Agent after | H60: case_involvement.Postcode | I60: WHERE case_involvement.TypeOfInvolvement = "Agent" , append to array
B61: Agent first name | C61: Agent address | D61: N/A | E61: N/A | F61: N/A | G61: Pull out from Agent after | H61: case_involvement.FirstName | I61: WHERE case_involvement.TypeOfInvolvement = "Agent" , append to array
B62: Agent last name | C62: Agent address | D62: N/A | E62: N/A | F62: N/A | G62: Pull out from Agent after | H62: case_involvement.LastName | I62: WHERE case_involvement.TypeOfInvolvement = "Agent" , append to array
B63: Agent email | C63: Agent address | D63: N/A | E63: N/A | F63: N/A | G63: Pull out from Agent after | H63: case_involvement.Email | I63: WHERE case_involvement.TypeOfInvolvement = "Agent" , append to array
B64: Agent phone | C64: Agent address | D64: N/A | E64: N/A | F64: N/A | G64: Pull out from Agent after | H64: case_involvement.TelephoneNumber | I64: WHERE case_involvement.TypeOfInvolvement = "Agent", append to array
A65: Applicant | B65: Applicant type | C65: Applicant type | D65: N/A | E65: N/A | F65: N/A | G65: Code after (individual vs org) | H65: N/A | I65: Process after
B66: Applicant organisation name | C66: Applicant organisation name | D66: Applicant | E66: Applicant | F66: Applicant | H66: case_involvement.ContactDetails | I66: WHERE case_involvement.TypeOfInvolvement = "Applicant" , append to array
B67: Applicant address 1 | C67: Applicant address | D67: N/A | E67: N/A | F67: N/A | G67: Pull out from Applicant after | H67: case_involvement.Address1 | I67: WHERE case_involvement.TypeOfInvolvement = "Applicant" , append to array
B68: Applicant address 2 | C68: Applicant address | D68: N/A | E68: N/A | F68: N/A | G68: Pull out from Applicant after | H68: case_involvement.Address2 | I68: WHERE case_involvement.TypeOfInvolvement = "Applicant" , append to array
B69: Applicant town or city | C69: Applicant address | D69: N/A | E69: N/A | F69: N/A | G69: Pull out from Applicant after | H69: case_involvement.City | I69: WHERE case_involvement.TypeOfInvolvement = "Applicant" , append to array
B70: Applicant county | C70: Applicant address | D70: N/A | E70: N/A | F70: N/A | G70: Pull out from Applicant after | H70: case_involvement.County | I70: WHERE case_involvement.TypeOfInvolvement = "Applicant" , append to array
B71: Applicant postcode | C71: Applicant address | D71: N/A | E71: N/A | F71: N/A | G71: Pull out from Applicant after | H71: case_involvement.Postcode | I71: WHERE case_involvement.TypeOfInvolvement = "Applicant" , append to array
B72: Applicant first name | C72: Applicant address | D72: N/A | E72: N/A | F72: N/A | G72: Pull out from Applicant after | H72: case_involvement.FirstName | I72: WHERE case_involvement.TypeOfInvolvement = "Applicant" , append to array
B73: Applicant last name | C73: Applicant address | D73: N/A | E73: N/A | F73: N/A | G73: Pull out from Applicant after | H73: case_involvement.LastName | I73: WHERE case_involvement.TypeOfInvolvement = "Applicant" , append to array
B74: Applicant email | C74: Applicant address | D74: N/A | E74: N/A | F74: N/A | G74: Pull out from Applicant after | H74: case_involvement.Email | I74: WHERE case_involvement.TypeOfInvolvement = "Applicant" , append to array
B75: Applicant phone | C75: Applicant address | D75: N/A | E75: N/A | F75: N/A | G75: Pull out from Applicant after | H75: case_involvement.TelephoneNumber | I75: WHERE case_involvement.TypeOfInvolvement = "Applicant" , append to array
A76: Case team | B76: Inspector 1 | C76: Appointed person / Inspector 1 | D76: Inspector | E76: Inspector | F76: Inspector / Planning Offcier | H76: case_involvement.FirstName, case_involvement.LastName | I76: WHERE case_involvement.TypeOfInvolvement in ('Inspector', 'Previous Inspector', 'Appointed Person') then append to array; we'll flatten out in to Inspector 2 and 3 after
B77: Date Inspector (1) allocated | C77: Date appointed person / inspector appointed | D77: N/A | E77: Date Insp allocated | F77: Date Insp assigned | H77: case_involvement_p.InvolvementStartDate | I77: WHERE case_involvement_p.TypeOfInvolvement in ('Inspector', 'Previous Inspector', 'Appointed Person') then append to array; we'll flatten out in to Inspector 2 and 3 after
B78: Inspector 2 | C78: Appointed person / Inspector 2 | D78: N/A | E78: N/A | F78: N/A | H78: N/A | I78: Process after
B79: Date Inspector (2) allocated | C79: Date appointed person / inspector appointed | D79: N/A | E79: N/A | F79: N/A | H79: N/A | I79: Process after
B80: Inspector 3 | C80: Appointed person / Inspector 3 | D80: N/A | E80: N/A | F80: N/A | H80: N/A | I80: Process after
B81: Date Inspector (3) allocated | C81: Date appointed person / inspector appointed | D81: N/A | E81: N/A | F81: N/A | H81: N/A | I81: Process after
B82: Case officer | C82: Case officer | D82: Case Officer | E82: Case Officer | F82: Case Officer | H82: case_involvement.FirstName, case_involvement.LastName | I82: WHERE case_involvement.TypeOfInvolvement in ('Case Officer', 'Case Manager', 'Case Administrator') , then append to array
B83: Planning officer | C83: Planning officer | D83: N/A | E83: N/A | F83: Inspector / Planning Offcier | G83: Probably need deleting after | H83: N/A | I83: N/A - take from S/S
B84: Assessor inspector | C84: Assessor inspector | D84: N/A | E84: N/A | F84: N/A | H84: N/A | I84: N/A - leave blank
B85: Reader | C85: Reader | D85: N/A | E85: Reader | F85: Reader | H85: N/A | I85: N/A - take from S/S
B86: Additional contacts - Other - Legal Officer - First name | C86: Additional contacts | D86: N/A | E86: N/A | F86: N/A | H86: case_involvement.FirstName | I86: WHERE case_involvement.TypeOfInvolvement = "Legal Officer" , append to array
B87: Additional contacts - Other - Legal Officer - Last name | D87: N/A | E87: N/A | F87: N/A | H87: case_involvement.LastName | I87: WHERE case_involvement.TypeOfInvolvement = "Legal Officer" , append to array
B88: Additional contacts - Other - Legal Officer - Phone number | D88: N/A | E88: N/A | F88: N/A | H88: case_involvement.TelephoneNumber | I88: WHERE case_involvement.TypeOfInvolvement = "Legal Officer" , append to array
B89: Additional contacts - Other - Legal Officer - Email | D89: N/A | E89: N/A | F89: N/A | H89: case_involvement.Email | I89: WHERE case_involvement.TypeOfInvolvement = "Legal Officer" , append to array
A90: Site details | B90: Site address 1 | C90: Site address | D90: Address | E90: Address | F90: Address | G90: Reformat after | H90: extended_data.SiteAddress | I90: Process after
B91: Site post code | C91: Site address | D91: N/A | E91: N/A | F91: N/A | G91: Pull out from Address after | H91: extended_data.SitePostcode
B92: Site coordinates - Easting | C92: Site coordinates | D92: N/A | E92: N/A | F92: N/A | H92: extended_data.SiteEasting
B93: Site coordinates - Northing | C93: Site coordinates | D93: N/A | E93: N/A | F93: N/A | H93: extended_data.SiteNorthing
B94: Area of site | C94: Area of site | D94: N/A | E94: N/A | F94: N/A | H94: extended_data.SiteArea
B95: Site area units | C95: Site area units | D95: N/A | E95: N/A | F95: N/A | H95: extended_data.SiteAreaUnitMeasurement
B96: Development description | C96: Development description | D96: Development | E96: Development | F96: Development | H96: basic_data.ApplicationDescription
A97: Details | B97: Likely issues | C97: Likely issues | D97: Likely issues | E97: Likely issues | F97: Likely issues | H97: N/A | I97: N/A - take from S/S
B98: Specialism | C98: Specialism | D98: Level & Specialism | E98: Level & Specialism | F98: Level & Specialism | G98: Reformat after | H98: N/A | I98: N/A - take from S/S
B99: Inspector band | C99: Inspector band | D99: Level & Specialism | E99: Level & Specialism | F99: Level & Specialism | G99: Reformat after | H99: N/A | I99: N/A - take from S/S
B100: Category | C100: Category | D100: N/A | E100: N/A | F100: N/A | H100: basic_data.ApplicationType
...

Sheet Sheet3
A2: Case reference | B2: Ref | C2: Ref | D2: Ref | F2: basic_data.CaseReference
A3: Status | B3: N/A | C3: N/A | D3: N/A | F3: N/A
A4: Status | B4: N/A | C4: N/A | D4: N/A | F4: basic_data.Status
A5: Stage | B5: N/A | C5: N/A | D5: N/A | F5: N/A
A6: Application phase | B6: Set to be "Pre-application" | C6: Set to be "Application" | D6: Set to be "Application" | F6: case_reference_list.caseCategory
A7: Application classification | B7: N/A | C7: Set to be "Major" | D7: Set to be "Non-major" | F7: N/A
A8: Application type | B8: Type of application | C8: Type of application | D8: Type of application | F8: basic_data.PermissionSought
A9: Application subtype | B9: N/A | C9: N/A | D9: N/A | E9: Planning Permission, Listed Building | F9: case_reference_list.caseCategory
A10: Notification received date | B10: Pre-notification date | C10: Pre-notification date | D10: Pre-notification date | F10: N/A | G10: Applicant organisation name
A11: Expected application submission date | B11: Expected submission date | C11: Expected submission date (not before) | D11: Expected submission date (not before) | F11: N/A | G11: Agent address
A12: Pre-app/Application received date | B12: Receipt date | C12: Receipt date | D12: Receipt date | F12: key_dates.DateReceived | G12: Applicant address
A13: Application acknowledged | B13: N/A | C13: Letter 7 sent to applicant | D13: Letter 7 sent to applicant | F13: N/A | G13: Agent address
A14: Further information requested | B14: N/A | C14: Letter 8 sent to applicant - invalid (if applicable) | D14: Letter 8 sent to applicant - invalid (if applicable) | F14: N/A | G14: Applicant address
A15: Date agreed for additional information | B15: N/A | C15: Date agreed for submission of additional docs | D15: Date agreed for submission of additional docs | F15: N/A | G15: Agent address
A16: Application valid date | B16: N/A | C16: Valid Date | D16: Valid / Validation Date | F16: key_dates.DateValid | G16: Applicant address
A17: Valid letters sent | B17: N/A | C17: Valid letters (17 & 9) to LPA and Applicant | D17: Valid letters (17 & 9) to LPA and Applicant | F17: key_dates.ConsultationsWithRelevantAuthoritiesDate | G17: Agent address
A18: LPA questionnaire sent date | B18: N/A | C18: Letter 16 and Q sent to LPA | D18: Letter 16 and Q sent to LPA | F18: key_dates.DateInfoSentToLPA | G18: Applicant address
A19: LPA questionnaire received date | B19: N/A | C19: LPA Q received | D19: LPA Q received | E19: Check | F19: key_dates.DateInfoReturnedFromLPA | G19: LPA contact
A20: Target publish date | B20: N/A | C20: Application published due date (valid + 5 working days) | D20: Application published due date (valid + 5 working days) | F20: N/A | G20: Agent address
A21: Publish date | B21: N/A | C21: Application documents published actual date | D21: Application documents published actual date | F21: key_dates.PublicityForApplicationsDate | G21: Applicant address
A22: Press notice date | B22: N/A | C22: PINS Interested parties press notice placed and TMP ref | D22: PINS Interested parties press notice placed and TMP ref | E22: Extract date | F22: key_dates.NewspaperAdvertDate
A23: Neighbours notified by LPA date | B23: N/A | C23: LPA Interested parties notification date | D23: LPA Interested parties notification date | F23: key_dates.DateNeighboursNotified | G23: LPA contact
A24: Neighbours notified by LPA date | B24: N/A | C24: LPA Interested parties notification date | D24: LPA Interested parties notification date | F24: key_dates.DateNeighboursNotified | G24: Agent address
A25: LPA interested parties deadline | B25: N/A | C25: LPA Interested parties deadline | D25: LPA Interested parties deadline | F25: N/A | G25: Applicant address
A26: Site notice by LPA date | B26: N/A | C26: N/A | D26: N/A | E26: Check | F26: key_dates.SiteNoticeDate | G26: Additional contacts
A27: Interested parties press notice deadline | B27: N/A | C27: PINS interested parties press notice deadline | D27: PINS interested parties press notice deadline | F27: N/A | G27: Appointed person / Inspector 1
A28: Mineral Applications | B28: N/A | C28: N/A | D28: N/A | E28: Check | F28: key_dates.MineralNotificationDate | G28: Case officer
A29: Interim findings date | B29: N/A | C29: Inspectors Interim findings (letter 25 to applicant) | D29: Inspectors Interim findings (letter 25 to applicant) | F29: N/A | G29: Date appointed person / inspector appointed
A30: Representations period | B30: N/A | C30: Consultations sent | D30: Consultations sent | F30: key_dates.RepresentationPeriodOpen | G30: LPA contact
A31: Representations period | B31: N/A | C31: Consultations deadline (see Statutory Consultees and Town Parish Council list for list of parties consulted) | D31: Consultations deadline (see Statutory Consultees and Town Parish Council list for list of parties consulted) | F31: key_dates.RepresentationPeriodClose | G31: Agent address
A32: Reconsultation details | B32: N/A | C32: Reconsultation details | D32: Reconsultation details | E32: Extract sent date | F32: N/A | G32: Applicant address
A33: Reconsultation details | B33: N/A | C33: Reconsultation details | D33: Reconsultation details | E33: Extract deadline date | F33: N/A
A34: Representations publish date | B34: N/A | C34: Representations, LPA Questionnaire published date and procedure decision (within 5 days of close of comment period) | D34: Representations, LPA Questionnaire published date and procedure decision (within 5 days of close of comment period) | F34: key_dates.RepresentationsPublishedDate | G34: Agent organisation name
A35: S106 submitted date | B35: N/A | C35: S106 submitted date | D35: S106 submitted date | F35: N/A | G35: Agent address
A36: Target decision date | B36: N/A | C36: Target decision date (13 or 16 weeks from valid) | D36: Target decision date (8 weeks from valid) | F36: key_dates.TargetDecisionDate | G36: Applicant address
A37: Extended target decision date | B37: N/A | C37: N/A | D37: N/A | F37: key_dates.EoTTargetDate | G37: LPA contact
A38: Recovered date | B38: N/A | C38: N/A | D38: N/A | F38: N/A | G38: Agent address
A39: Site visit type | B39: Site Visit | C39: Inspector USV or ARSV date (if needed) | D39: Inspector USV or ARSV date (if needed) | E39: Extract type | F39: N/A | G39: Applicant address
A40: Site visit | B40: Site Visit | C40: Inspector USV or ARSV date (if needed) | D40: Inspector USV or ARSV date (if needed) | E40: Extract date | F40: N/A
A41: Withdrawn date | B41: N/A | C41: N/A | D41: N/A | E41: Process after | F41: N/A | G41: Application phase
A42: Turned away date | B42: N/A | C42: N/A | D42: N/A | E42: Process after | F42: N/A | G42: Application subtype
A43: Pre-application advice | B43: N/A | C43: Pre-application advice? | D43: Pre-application advice? | E43: Process after | F43: basic_data.PreApplicationAdviceGiven
A44: Pre-application received date | B44: Receipt date | C44: N/A | D44: N/A | E44: Do this after for Major/Non-major as will have to be the receipt date of the pre-app that is linked to case | F44: N/A
A45: Pre-application reference | B45: Ref | C45: Pre-application reference | D45: Pre-application reference | F45: N/A
A46: LPA contact | B46: LPA | C46: LPA | D46: LPA | F46: basic_data.LPAName
A47: LPA contact | B47: N/A | C47: N/A | D47: N/A | F47: case_involvement.FirstName
A48: LPA contact | B48: N/A | C48: N/A | D48: N/A | F48: case_involvement.LastName
A49: LPA contact | B49: N/A | C49: N/A | D49: N/A | F49: case_involvement.TelephoneOffice
A50: LPA contact | B50: N/A | C50: N/A | D50: N/A | F50: case_involvement.Email
A51: Secondary LPA contact | B51: N/A | C51: N/A | D51: N/A | F51: N/A
A52: Secondary LPA contact | B52: N/A | C52: N/A | D52: N/A | F52: N/A
A53: Secondary LPA contact | B53: N/A | C53: N/A | D53: N/A | F53: N/A
A54: Secondary LPA contact | B54: N/A | C54: N/A | D54: N/A | F54: N/A
A55: Secondary LPA contact | B55: N/A | C55: N/A | D55: N/A | F55: N/A
A56: Agent organisation name | B56: Agent | C56: Agent | D56: Agent | F56: case_involvement.Name
A57: Agent address | B57: N/A | C57: N/A | D57: N/A | E57: Pull out from Agent after | F57: case_involvement.Address1
A58: Agent address | B58: N/A | C58: N/A | D58: N/A | E58: Pull out from Agent after | F58: case_involvement.Address2
A59: Agent address | B59: N/A | C59: N/A | D59: N/A | E59: Pull out from Agent after | F59: case_involvement.City
A60: Agent address | B60: N/A | C60: N/A | D60: N/A | E60: Pull out from Agent after | F60: case_involvement.County
A61: Agent address | B61: N/A | C61: N/A | D61: N/A | E61: Pull out from Agent after | F61: case_involvement.PostCode
A62: Agent address | B62: N/A | C62: N/A | D62: N/A | E62: Pull out from Agent after | F62: case_involvement.FirstName
A63: Agent address | B63: N/A | C63: N/A | D63: N/A | E63: Pull out from Agent after | F63: case_involvement.LastName
A64: Agent address | B64: N/A | C64: N/A | D64: N/A | E64: Pull out from Agent after | F64: case_involvement.Email
A65: Agent address | B65: N/A | C65: N/A | D65: N/A | E65: Pull out from Agent after | F65: case_involvement.TelephoneOffice
A66: Applicant type | B66: N/A | C66: N/A | D66: N/A | E66: Code after (individual vs org) | F66: N/A
A67: Applicant organisation name | B67: Applicant | C67: Applicant | D67: Applicant | F67: case_involvement.ContactDetails
A68: Applicant address | B68: N/A | C68: N/A | D68: N/A | E68: Pull out from Applicant after | F68: case_involvement.Address1
A69: Applicant address | B69: N/A | C69: N/A | D69: N/A | E69: Pull out from Applicant after | F69: case_involvement.Address2
A70: Applicant address | B70: N/A | C70: N/A | D70: N/A | E70: Pull out from Applicant after | F70: case_involvement.City
A71: Applicant address | B71: N/A | C71: N/A | D71: N/A | E71: Pull out from Applicant after | F71: case_involvement.County
A72: Applicant address | B72: N/A | C72: N/A | D72: N/A | E72: Pull out from Applicant after | F72: case_involvement.PostCode
A73: Applicant address | B73: N/A | C73: N/A | D73: N/A | E73: Pull out from Applicant after | F73: case_involvement.FirstName
A74: Applicant address | B74: N/A | C74: N/A | D74: N/A | E74: Pull out from Applicant after | F74: case_involvement.LastName
A75: Applicant address | B75: N/A | C75: N/A | D75: N/A | E75: Pull out from Applicant after | F75: case_involvement.TelephoneOffice
A76: Applicant address | B76: N/A | C76: N/A | D76: N/A | E76: Pull out from Applicant after | F76: case_involvement.Email
A77: Appointed person / Inspector 1 | B77: Inspector | C77: Inspector | D77: Inspector / Planning Offcier | F77: case_involvement.FirstName, case_involvement.LastName
A78: Date appointed person / inspector appointed | B78: N/A | C78: Date Insp allocated | D78: Date Insp assigned | F78: case_involvement.InvolvementStartDate
A79: Appointed person / Inspector 2 | B79: N/A | C79: N/A | D79: N/A | F79: N/A
A80: Date appointed person / inspector appointed | B80: N/A | C80: N/A | D80: N/A | F80: N/A
A81: Appointed person / Inspector 3 | B81: N/A | C81: N/A | D81: N/A | F81: N/A
A82: Date appointed person / inspector appointed | B82: N/A | C82: N/A | D82: N/A | F82: N/A
A83: Case officer | B83: Case Officer | C83: Case Officer | D83: Case Officer | F83: case_involvement.FirstName, case_involvement.LastName
A84: Planning officer | B84: N/A | C84: N/A | D84: Inspector / Planning Offcier | E84: Probably need deleting after | F84: N/A
A85: Assessor inspector | B85: N/A | C85: N/A | D85: N/A | F85: N/A
A86: Reader | B86: N/A | C86: Reader | D86: Reader | F86: N/A
A87: Additional contacts | B87: N/A | C87: N/A | D87: N/A | F87: case_involvement.FirstName
B88: N/A | C88: N/A | D88: N/A | F88: case_involvement.LastName
B89: N/A | C89: N/A | D89: N/A | F89: case_involvement.TelephoneOffice
B90: N/A | C90: N/A | D90: N/A | F90: case_involvement.Email
A91: Site address | B91: Address | C91: Address | D91: Address | E91: Reformat after | F91: extended_data.SiteAddress
A92: Site address | B92: N/A | C92: N/A | D92: N/A | E92: Pull out from Address after | F92: extended_data.SiteAddress
A93: Site address | B93: N/A | C93: N/A | D93: N/A | E93: Pull out from Address after | F93: extended_data.SiteAddress
A94: Site address | B94: N/A | C94: N/A | D94: N/A | E94: Pull out from Address after | F94: extended_data.SiteAddress
A95: Site address | B95: N/A | C95: N/A | D95: N/A | E95: Pull out from Address after | F95: extended_data.SitePostcode
A96: Site coordinates | B96: N/A | C96: N/A | D96: N/A | F96: extended_data.SiteEasting
A97: Site coordinates | B97: N/A | C97: N/A | D97: N/A | F97: extended_data.SiteNorthing
A98: Area of site | B98: N/A | C98: N/A | D98: N/A | F98: extended_data.SiteArea
A99: Site area units | B99: N/A | C99: N/A | D99: N/A | F99: extended_data.SiteAreaUnitMeasurement
A100: Development description | B100: Development | C100: Development | D100: Development | F100: basic_data.ApplicationDescription
A101: Likely issues | B101: Likely issues | C101: Likely issues | D101: Likely issues | F101: N/A
...

Sheet case_involvement
A1: TypeOfInvolvement(p) | B1: TypeOfInvolvement(o)
A2: Agent | B2: Case Officer
A3: Inspector | B3: Case Officer
A4: Appointed Person | B4: LPA
A5: Applicant | B5: Applicant
A6: Planning Officer
A7: Previous Inspector
A8: Case Administrator
A9: Case Manager
A10: Case Officer
A11: Legal Officer

Sheet Sheet2
A1: Tab | B1: Column | D1: Tab | E1: Column | G1: Tab | H1: Column
A2: Preapp | B2: Ref | C2: =MATCH(B2,Lookup!D:D,0) -> 2 | D2: Major | E2: Ref | F2: =MATCH(E2,Lookup!E:E,0) -> 2 | G2: Non-major | H2: Ref | I2: =MATCH(H2,Lookup!F:F,0) -> 2
A3: Preapp | B3: Address | C3: =MATCH(B3,Lookup!D:D,0) -> 90 | D3: Major | E3: Address | F3: =MATCH(E3,Lookup!E:E,0) -> 90 | G3: Non-major | H3: Address | I3: =MATCH(H3,Lookup!F:F,0) -> 90
A4: Preapp | B4: LPA | C4: =MATCH(B4,Lookup!D:D,0) -> 45 | D4: Major | E4: LPA | F4: =MATCH(E4,Lookup!E:E,0) -> 45 | G4: Non-major | H4: LPA | I4: =MATCH(H4,Lookup!F:F,0) -> 45
A5: Preapp | B5: Likely issues | C5: =MATCH(B5,Lookup!D:D,0) -> 97 | D5: Major | E5: Likely issues | F5: =MATCH(E5,Lookup!E:E,0) -> 97 | G5: Non-major | H5: Likely Issues | I5: =MATCH(H5,Lookup!F:F,0) -> 97
A6: Preapp | B6: Level & Specialism | C6: =MATCH(B6,Lookup!D:D,0) -> 98 | D6: Major | E6: Level & Specialism | F6: =MATCH(E6,Lookup!E:E,0) -> 98 | G6: Non-major | H6: Level & Specialism | I6: =MATCH(H6,Lookup!F:F,0) -> 98
A7: Preapp | B7: Applicant | C7: =MATCH(B7,Lookup!D:D,0) -> 66 | D7: Major | E7: Applicant | F7: =MATCH(E7,Lookup!E:E,0) -> 66 | G7: Non-major | H7: Applicant | I7: =MATCH(H7,Lookup!F:F,0) -> 66
A8: Preapp | B8: Agent | C8: =MATCH(B8,Lookup!D:D,0) -> 55 | D8: Major | E8: Agent | F8: =MATCH(E8,Lookup!E:E,0) -> 55 | G8: Non-major | H8: Agent | I8: =MATCH(H8,Lookup!F:F,0) -> 55
A9: Preapp | B9: Type of application | C9: =MATCH(B9,Lookup!D:D,0) -> 8 | D9: Major | E9: Type of application | F9: =MATCH(E9,Lookup!E:E,0) -> 8 | G9: Non-major | H9: Type of application | I9: =MATCH(H9,Lookup!F:F,0) -> 8
A10: Preapp | B10: Pre-notification date | C10: =MATCH(B10,Lookup!D:D,0) -> 10 | D10: Major | E10: Pre-application advice? | F10: =MATCH(E10,Lookup!E:E,0) -> 42 | G10: Non-major | H10: Pre-application advice? | I10: =MATCH(H10,Lookup!F:F,0) -> 42
A11: Preapp | B11: Expected submission date | C11: =MATCH(B11,Lookup!D:D,0) -> 11 | D11: Major | E11: Pre-application reference | F11: =MATCH(E11,Lookup!E:E,0) -> 44 | G11: Non-major | H11: Pre-application reference | I11: =MATCH(H11,Lookup!F:F,0) -> 44
A12: Preapp | B12: Receipt date | C12: =MATCH(B12,Lookup!D:D,0) -> 12 | D12: Major | E12: Estimated fee | F12: =MATCH(E12,Lookup!E:E,0) -> 188 | G12: Non-major | H12: Estimated fee | I12: =MATCH(H12,Lookup!F:F,0) -> 188
A13: Preapp | B13: Development | C13: =MATCH(B13,Lookup!D:D,0) -> 96 | D13: Major | E13: Pre-notification date | F13: =MATCH(E13,Lookup!E:E,0) -> 10 | G13: Non-major | H13: Pre-notification date | I13: =MATCH(H13,Lookup!F:F,0) -> 10
... A28: Preapp | B28: Amount Invoiced | C28: =MATCH(B28,Lookup!D:D,0) -> 127 | D28: Major | E28: Valid Date | F28: =MATCH(E28,Lookup!E:E,0) -> 16 | G28: Non-major | H28: Any confidential docs? | I28: =MATCH(H28,Lookup!F:F,0) -> 198
D29: Major | E29: Application published due date (valid + 5 working days) | F29: =MATCH(E29,Lookup!E:E,0) -> 20 | G29: Non-major | H29: Application documents published actual date | I29: =MATCH(H29,Lookup!F:F,0) -> 21
D30: Major | E30: Any confidential docs? | F30: =MATCH(E30,Lookup!E:E,0) -> 198 | G30: Non-major | H30: Valid letters (17 & 9) to LPA and Applicant | I30: =MATCH(H30,Lookup!F:F,0) -> 17
D31: Major | E31: Application documents published actual date | F31: =MATCH(E31,Lookup!E:E,0) -> 21 | G31: Non-major | H31: LPA Q received | I31: =MATCH(H31,Lookup!F:F,0) -> 19
D32: Major | E32: Valid letters (17 & 9) to LPA and Applicant | F32: =MATCH(E32,Lookup!E:E,0) -> 17 | G32: Non-major | H32: LPA CIL response | I32: =MATCH(H32,Lookup!F:F,0) -> 107
D33: Major | E33: LPA Q received | F33: =MATCH(E33,Lookup!E:E,0) -> 19 | G33: Non-major | H33: CIL amount | I33: =MATCH(H33,Lookup!F:F,0) -> 108
D34: Major | E34: LPA CIL response | F34: =MATCH(E34,Lookup!E:E,0) -> 107 | G34: Non-major | H34: EIA - screening request sent to EST (confirm with EST when application valid) | I34: =MATCH(H34,Lookup!F:F,0) -> 110
D35: Major | E35: EIA - screening request sent to EST (confirm with EST when application valid) | F35: =MATCH(E35,Lookup!E:E,0) -> 110 | G35: Non-major | H35: EIA outcome (publish any letter to gov.uk) | I35: =MATCH(H35,Lookup!F:F,0) -> 111
D36: Major | E36: EIA outcome (publish any letter to gov.uk) | F36: =MATCH(E36,Lookup!E:E,0) -> 111 | G36: Non-major | H36: Consultations sent | I36: =MATCH(H36,Lookup!F:F,0) -> 29
D37: Major | E37: Consultations sent | F37: =MATCH(E37,Lookup!E:E,0) -> 29 | G37: Non-major | H37: Consultations deadline (see Statutory Consultees and Town Parish Council list for list of parties consulted) | I37: =MATCH(H37,Lookup!F:F,0) -> 30
D38: Major | E38: Consultations deadline (see Statutory Consultees and Town Parish Council list for list of parties consulted) | F38: =MATCH(E38,Lookup!E:E,0) -> 30 | G38: Non-major | H38: LPA Interested parties notification date | I38: =MATCH(H38,Lookup!F:F,0) -> 23
D39: Major | E39: LPA Interested parties notification date | F39: =MATCH(E39,Lookup!E:E,0) -> 23 | G39: Non-major | H39: LPA Interested parties deadline | I39: =MATCH(H39,Lookup!F:F,0) -> 24
D40: Major | E40: LPA Interested parties deadline | F40: =MATCH(E40,Lookup!E:E,0) -> 24 | G40: Non-major | H40: PINS Interested parties press notice placed and TMP ref | I40: =MATCH(H40,Lookup!F:F,0) -> 22
... D58: Major | E58: Grant/Refuse | F58: =MATCH(E58,Lookup!E:E,0) -> 138 | G58: Non-major | H58: Comments/Notes | I58: =MATCH(H58,Lookup!F:F,0) -> 142
D59: Major | E59: Time taken from valid to decision | F59: =MATCH(E59,Lookup!E:E,0) -> 195
D60: Major | E60: Comments/Notes | F60: =MATCH(E60,Lookup!E:E,0) -> 142

Sheet Sheet1
A1: Template LEGACY cases S62A | C1: Horizon | D1: Notes
B2: Case reference | C2: Case reference
A3: Case progress | B3: Pre-application status | D3: New column, need to find horizon equivalent if it does come from there
B4: Application Status
B5: Stage | D5: Need to establish column in horizon
A6: Case type | B6: Application phase
B7: Application classification
B8: Application type
B9: Application subtype
A10: Dates | B10: Notification received date
B11: Expected submission date
B12: Pre-app/Application received date
B13: Application acknowledged
B14: Further info requested
B15: Date agreed for additional info
B16: Application valid
B17: Valid letters sent
B18: LPA questionnaire sent
B19: LPA questionnaire rec'd date
B20: Target publish date
B21: Publish date
B22: Press notice date
... B40: Site visit date
A41: Closed status dates | B41: Withdrawn date
B42: Turned away date
A43: Pre-application details | B43: Pre-application advice requested
B44: Pre-app received date
B45: Pre-app reference
A46: LPA | B46: LPA
B47: LPA contact - First name
B48: LPA contact - Last name
B49: LPA contact - Phone number
B50: LPA contact - Email
A51: Secondary LPA | B51: Secondary LPA
B52: Secondary LPA - First name
B53: Secondary LPA - Last name
B54: Secondary LPA - Phone number
B55: Secondary LPA - Email
A56: Agent | B56: Agent organisation name
B57: Agent address 1
B58: Agent address 2
B59: Agent town or city
B60: Agent county
B61: Agent postcode
B62: Agent first name
B63: Agent last name
B64: Agent email
B65: Agent phone
A66: Applicant | B66: Applicant type
B67: Applicant organisation name
B68: Applicant address 1
B69: Applicant address 2
B70: Applicant town or city
B71: Applicant county
B72: Applicant postcode
B73: Applicant first name
B74: Applicant last name
B75: Applicant email
B76: Applicant phone
A77: Case team | B77: Inspector 1
B78: Date Inspector (1) allocated
B79: Inspector 2
B80: Date Inspector (2) allocated
B81: Inspector 3
B82: Date Inspector (3) allocated
B83: Case officer
B84: Planning officer
B85: Assessor inspector
B86: Reader
A87: Site details | B87: Site address 1
B88: Site address 2
B89: Site town or city
B90: Site county
B91: Site post code
B92: Site coordinates - Easting
B93: Site coordinates - Northing
B94: Area of site
B95: Site area units
B96: Development description
A97: Details | B97: Likely issues
B98: Specialism
B99: Inspector band
B100: Category
B101: Site visibile from public land
B102: LPA reference | D102: same as LPA code
B103: Listed building reference
B104: Green belt
B105: Health and safety issues
B106: Procedure
B107: CIL liable
B108: CIL amount
B109: BNG Exempt
A110: Environmental Impact Assessment | B110: EIA screening
B111: EIA screening outcome
B112: Date Environmental Statement rec'd
A113: Procedure/Event | B113: Notice of procedure date
B114: Hearing date
B115: Hearing notification date
B116: Hearing issues report published date
B117: Hearing duration - prep (days)
...
