Workbook

Sheet Lookup
A1: Template LEGACY cases S62A | C1: Pre-application - DONE | D1: Application (Major) | E1: Application (Non Major) | F1: Horizon | G1: Notes
B2: Case reference | C2: Ref | D2: Ref | E2: Ref
A3: Case progress | B3: Pre-application status | C3: N/A | D3: N/A | E3: N/A
B4: Application Status | C4: N/A | D4: N/A | E4: N/A
B5: Stage | C5: N/A | D5: N/A | E5: N/A
A6: Case type | B6: Pre-application or application | C6: Set to be "pre-application" | D6: Set to be "application" | E6: Set to be "application"
B7: Application classification | C7: N/A | D7: Set to be "Major" | E7: Set to be "Non-major"
B8: Application type | C8: Type of application | D8: Type of application | E8: Type of application
B9: Application subtype | C9: N/A | D9: N/A | E9: N/A | G9: Planning Permission, Listed Building
A10: Dates | B10: Notification received date | C10: Pre-notification date | D10: Pre-notification date | E10: Pre-notification date
B11: Expected submission date | C11: Expected submission date | D11: Expected submission date (not before) | E11: Expected submission date (not before)
B12: Pre-app/Application received date | C12: Receipt date | D12: Receipt date | E12: Receipt date
B13: Application acknowledged | C13: N/A | D13: Letter 7 sent to applicant | E13: Letter 7 sent to applicant
B14: Further info requested | C14: N/A | D14: Letter 8 sent to applicant - invalid (if applicable) | E14: Letter 8 sent to applicant - invalid (if applicable)
B15: Date agreed for additional info | C15: N/A | D15: Date agreed for submission of additional docs | E15: Date agreed for submission of additional docs
B16: Application valid | C16: N/A | D16: Valid Date | E16: Valid / Validation Date
B17: Valid letters sent | C17: N/A | D17: Valid letters (17 & 9) to LPA and Applicant | E17: Valid letters (17 & 9) to LPA and Applicant
B18: LPA questionnaire sent | C18: N/A | D18: Letter 16 and Q sent to LPA | E18: Letter 16 and Q sent to LPA
B19: LPA questionnaire rec'd date | C19: N/A | D19: LPA Q received | E19: LPA Q received | G19: Check
B20: Target publish date | C20: N/A | D20: Application published due date (valid + 5 working days) | E20: Application published due date (valid + 5 working days)
B21: Publish date | C21: N/A | D21: Application documents published actual date | E21: Application documents published actual date
B22: Press notice date | C22: N/A | D22: PINS Interested parties press notice placed and TMP ref | E22: PINS Interested parties press notice placed and TMP ref | G22: Extract date
B23: Neighbours notified by LPA date | C23: N/A | D23: LPA Interested parties notification date | E23: LPA Interested parties notification date
B24: Neighbours notified by LPA date | C24: N/A | D24: LPA Interested parties notification date | E24: LPA Interested parties notification date
B25: LPA interested parties deadline | C25: N/A | D25: LPA Interested parties deadline | E25: LPA Interested parties deadline
B26: Site notice by LPA date | C26: N/A | D26: N/A | E26: N/A | G26: Check
B27: Interested parties press notice deadline | C27: N/A | D27: PINS interested parties press notice deadline | E27: PINS interested parties press notice deadline
B28: Mineral Applications date | C28: N/A | D28: N/A | E28: N/A | G28: Check
B29: Interim findings date | C29: N/A | D29: Inspectors Interim findings (letter 25 to applicant) | E29: Inspectors Interim findings (letter 25 to applicant)
B30: Representations period - start | C30: N/A | D30: Consultations sent | E30: Consultations sent
B31: Representations period - End | C31: N/A | D31: Consultations deadline (see Statutory Consultees and Town Parish Council list for list of parties consulted) | E31: Consultations deadline (see Statutory Consultees and Town Parish Council list for list of parties consulted)
B32: Reconsultation details sent date | C32: N/A | D32: Reconsultation details | E32: Reconsultation details | G32: Extract sent date
B33: Reconsultation details deadline date | C33: N/A | D33: Reconsultation details | E33: Reconsultation details | G33: Extract deadline date
B34: Representations publish date | C34: N/A | D34: Representations, LPA Questionnaire published date and procedure decision (within 5 days of close of comment period) | E34: Representations, LPA Questionnaire published date and procedure decision (within 5 days of close of comment period)
B35: S106 submitted date | C35: N/A | D35: S106 submitted date | E35: S106 submitted date
B36: Target decision date | C36: N/A | D36: Target decision date (13 or 16 weeks from valid) | E36: Target decision date (8 weeks from valid)
B37: Extended target decision date | C37: N/A | D37: N/A | E37: N/A
B38: Recovered date | C38: N/A | D38: N/A | E38: N/A
B39: Site visit type | C39: Site Visit | D39: Inspector USV or ARSV date (if needed) | E39: Inspector USV or ARSV date (if needed) | G39: Extract type
B40: Site visit date | C40: Site Visit | D40: Inspector USV or ARSV date (if needed) | E40: Inspector USV or ARSV date (if needed) | G40: Extract date
A41: Closed status dates | B41: Withdrawn date | C41: N/A | D41: N/A | E41: N/A | G41: Process after
B42: Turned away date | C42: N/A | D42: N/A | E42: N/A | G42: Process after
A43: Pre-application details | B43: Pre-application advice requested | C43: N/A | D43: Pre-application advice? | E43: Pre-application advice? | G43: Process after
B44: Pre-app received date | C44: Receipt date | D44: N/A | E44: N/A | G44: Do this after for Major/Non-major as will have to be the receipt date of the pre-app that is linked to case
B45: Pre-app reference | C45: Ref | D45: Pre-application reference | E45: Pre-application reference
A46: LPA | B46: LPA | C46: LPA | D46: LPA | E46: LPA
B47: LPA contact - First name | C47: N/A | D47: N/A | E47: N/A
B48: LPA contact - Last name | C48: N/A | D48: N/A | E48: N/A
B49: LPA contact - Phone number | C49: N/A | D49: N/A | E49: N/A
B50: LPA contact - Email | C50: N/A | D50: N/A | E50: N/A
A51: Secondary LPA | B51: Secondary LPA | C51: N/A | D51: N/A | E51: N/A
B52: Secondary LPA - First name | C52: N/A | D52: N/A | E52: N/A
B53: Secondary LPA - Last name | C53: N/A | D53: N/A | E53: N/A
B54: Secondary LPA - Phone number | C54: N/A | D54: N/A | E54: N/A
B55: Secondary LPA - Email | C55: N/A | D55: N/A | E55: N/A
A56: Agent | B56: Agent organisation name | C56: Agent | D56: Agent | E56: Agent
B57: Agent address 1 | C57: N/A | D57: N/A | E57: N/A | G57: Pull out from Agent after
B58: Agent address 2 | C58: N/A | D58: N/A | E58: N/A | G58: Pull out from Agent after
B59: Agent town or city | C59: N/A | D59: N/A | E59: N/A | G59: Pull out from Agent after
B60: Agent county | C60: N/A | D60: N/A | E60: N/A | G60: Pull out from Agent after
B61: Agent postcode | C61: N/A | D61: N/A | E61: N/A | G61: Pull out from Agent after
B62: Agent first name | C62: N/A | D62: N/A | E62: N/A | G62: Pull out from Agent after
B63: Agent last name | C63: N/A | D63: N/A | E63: N/A | G63: Pull out from Agent after
B64: Agent email | C64: N/A | D64: N/A | E64: N/A | G64: Pull out from Agent after
B65: Agent phone | C65: N/A | D65: N/A | E65: N/A | G65: Pull out from Agent after
A66: Applicant | B66: Applicant type | C66: N/A | D66: N/A | E66: N/A | G66: Code after (individual vs org)
B67: Applicant organisation name | C67: Applicant | D67: Applicant | E67: Applicant
B68: Applicant address 1 | C68: N/A | D68: N/A | E68: N/A | G68: Pull out from Applicant after
B69: Applicant address 2 | C69: N/A | D69: N/A | E69: N/A | G69: Pull out from Applicant after
B70: Applicant town or city | C70: N/A | D70: N/A | E70: N/A | G70: Pull out from Applicant after
B71: Applicant county | C71: N/A | D71: N/A | E71: N/A | G71: Pull out from Applicant after
B72: Applicant postcode | C72: N/A | D72: N/A | E72: N/A | G72: Pull out from Applicant after
B73: Applicant first name | C73: N/A | D73: N/A | E73: N/A | G73: Pull out from Applicant after
B74: Applicant last name | C74: N/A | D74: N/A | E74: N/A | G74: Pull out from Applicant after
B75: Applicant email | C75: N/A | D75: N/A | E75: N/A | G75: Pull out from Applicant after
B76: Applicant phone | C76: N/A | D76: N/A | E76: N/A | G76: Pull out from Applicant after
A77: Case team | B77: Inspector 1 | C77: Inspector | D77: Inspector | E77: Inspector / Planning Offcier
B78: Date Inspector (1) allocated | C78: N/A | D78: Date Insp allocated | E78: Date Insp assigned
B79: Inspector 2 | C79: N/A | D79: N/A | E79: N/A
B80: Date Inspector (2) allocated | C80: N/A | D80: N/A | E80: N/A
B81: Inspector 3 | C81: N/A | D81: N/A | E81: N/A
B82: Date Inspector (3) allocated | C82: N/A | D82: N/A | E82: N/A
B83: Case officer | C83: Case Officer | D83: Case Officer | E83: Case Officer
B84: Planning officer | C84: N/A | D84: N/A | E84: Inspector / Planning Offcier | G84: Probably need deleting after
B85: Assessor inspector | C85: Case Officer | D85: Case Officer | E85: Case Officer
B86: Reader | C86: N/A | D86: Reader | E86: Reader
A87: Site details | B87: Site address 1 | C87: Address | D87: Address | E87: Address | G87: Reformat after
B88: Site address 2 | C88: N/A | D88: N/A | E88: N/A | G88: Pull out from Address after
B89: Site town or city | C89: N/A | D89: N/A | E89: N/A | G89: Pull out from Address after
B90: Site county | C90: N/A | D90: N/A | E90: N/A | G90: Pull out from Address after
B91: Site post code | C91: N/A | D91: N/A | E91: N/A | G91: Pull out from Address after
B92: Site coordinates - Easting | C92: N/A | D92: N/A | E92: N/A
B93: Site coordinates - Northing | C93: N/A | D93: N/A | E93: N/A
B94: Area of site | C94: N/A | D94: N/A | E94: N/A
B95: Site area units | C95: N/A | D95: N/A | E95: N/A
B96: Development description | C96: Development | D96: Development | E96: Development
A97: Details | B97: Likely issues | C97: Likely issues | D97: Likely issues | E97: Likely issues
B98: Specialism | C98: Level & Specialism | D98: Level & Specialism | E98: Level & Specialism | G98: Reformat after
B99: Inspector band | C99: Level & Specialism | D99: Level & Specialism | E99: Level & Specialism | G99: Reformat after
B100: Category | C100: N/A | D100: N/A | E100: N/A
...

Sheet Sheet2
A1: Tab | B1: Column | D1: Tab | E1: Column | G1: Tab | H1: Column
A2: Preapp | B2: Ref | C2: =MATCH(B2,Lookup!C:C,0) -> 2 | D2: Major | E2: Ref | F2: =MATCH(E2,Lookup!D:D,0) -> 2 | G2: Non-major | H2: Ref | I2: =MATCH(H2,Lookup!E:E,0) -> 2
A3: Preapp | B3: Address | C3: =MATCH(B3,Lookup!C:C,0) -> 87 | D3: Major | E3: Address | F3: =MATCH(E3,Lookup!D:D,0) -> 87 | G3: Non-major | H3: Address | I3: =MATCH(H3,Lookup!E:E,0) -> 87
A4: Preapp | B4: LPA | C4: =MATCH(B4,Lookup!C:C,0) -> 46 | D4: Major | E4: LPA | F4: =MATCH(E4,Lookup!D:D,0) -> 46 | G4: Non-major | H4: LPA | I4: =MATCH(H4,Lookup!E:E,0) -> 46
A5: Preapp | B5: Likely issues | C5: =MATCH(B5,Lookup!C:C,0) -> 97 | D5: Major | E5: Likely issues | F5: =MATCH(E5,Lookup!D:D,0) -> 97 | G5: Non-major | H5: Likely Issues | I5: =MATCH(H5,Lookup!E:E,0) -> 97
A6: Preapp | B6: Level & Specialism | C6: =MATCH(B6,Lookup!C:C,0) -> 98 | D6: Major | E6: Level & Specialism | F6: =MATCH(E6,Lookup!D:D,0) -> 98 | G6: Non-major | H6: Level & Specialism | I6: =MATCH(H6,Lookup!E:E,0) -> 98
A7: Preapp | B7: Applicant | C7: =MATCH(B7,Lookup!C:C,0) -> 67 | D7: Major | E7: Applicant | F7: =MATCH(E7,Lookup!D:D,0) -> 67 | G7: Non-major | H7: Applicant | I7: =MATCH(H7,Lookup!E:E,0) -> 67
A8: Preapp | B8: Agent | C8: =MATCH(B8,Lookup!C:C,0) -> 56 | D8: Major | E8: Agent | F8: =MATCH(E8,Lookup!D:D,0) -> 56 | G8: Non-major | H8: Agent | I8: =MATCH(H8,Lookup!E:E,0) -> 56
A9: Preapp | B9: Type of application | C9: =MATCH(B9,Lookup!C:C,0) -> 8 | D9: Major | E9: Type of application | F9: =MATCH(E9,Lookup!D:D,0) -> 8 | G9: Non-major | H9: Type of application | I9: =MATCH(H9,Lookup!E:E,0) -> 8
A10: Preapp | B10: Pre-notification date | C10: =MATCH(B10,Lookup!C:C,0) -> 10 | D10: Major | E10: Pre-application advice? | F10: =MATCH(E10,Lookup!D:D,0) -> 43 | G10: Non-major | H10: Pre-application advice? | I10: =MATCH(H10,Lookup!E:E,0) -> 43
A11: Preapp | B11: Expected submission date | C11: =MATCH(B11,Lookup!C:C,0) -> 11 | D11: Major | E11: Pre-application reference | F11: =MATCH(E11,Lookup!D:D,0) -> 45 | G11: Non-major | H11: Pre-application reference | I11: =MATCH(H11,Lookup!E:E,0) -> 45
A12: Preapp | B12: Receipt date | C12: =MATCH(B12,Lookup!C:C,0) -> 12 | D12: Major | E12: Estimated fee | F12: =MATCH(E12,Lookup!D:D,0) -> 188 | G12: Non-major | H12: Estimated fee | I12: =MATCH(H12,Lookup!E:E,0) -> 188
A13: Preapp | B13: Development | C13: =MATCH(B13,Lookup!C:C,0) -> 96 | D13: Major | E13: Pre-notification date | F13: =MATCH(E13,Lookup!D:D,0) -> 10 | G13: Non-major | H13: Pre-notification date | I13: =MATCH(H13,Lookup!E:E,0) -> 10
... A28: Preapp | B28: Amount Invoiced | C28: =MATCH(B28,Lookup!C:C,0) -> 127 | D28: Major | E28: Valid Date | F28: =MATCH(E28,Lookup!D:D,0) -> 16 | G28: Non-major | H28: Any confidential docs? | I28: =MATCH(H28,Lookup!E:E,0) -> 198
D29: Major | E29: Application published due date (valid + 5 working days) | F29: =MATCH(E29,Lookup!D:D,0) -> 20 | G29: Non-major | H29: Application documents published actual date | I29: =MATCH(H29,Lookup!E:E,0) -> 21
D30: Major | E30: Any confidential docs? | F30: =MATCH(E30,Lookup!D:D,0) -> 198 | G30: Non-major | H30: Valid letters (17 & 9) to LPA and Applicant | I30: =MATCH(H30,Lookup!E:E,0) -> 17
D31: Major | E31: Application documents published actual date | F31: =MATCH(E31,Lookup!D:D,0) -> 21 | G31: Non-major | H31: LPA Q received | I31: =MATCH(H31,Lookup!E:E,0) -> 19
D32: Major | E32: Valid letters (17 & 9) to LPA and Applicant | F32: =MATCH(E32,Lookup!D:D,0) -> 17 | G32: Non-major | H32: LPA CIL response | I32: =MATCH(H32,Lookup!E:E,0) -> 107
D33: Major | E33: LPA Q received | F33: =MATCH(E33,Lookup!D:D,0) -> 19 | G33: Non-major | H33: CIL amount | I33: =MATCH(H33,Lookup!E:E,0) -> 108
D34: Major | E34: LPA CIL response | F34: =MATCH(E34,Lookup!D:D,0) -> 107 | G34: Non-major | H34: EIA - screening request sent to EST (confirm with EST when application valid) | I34: =MATCH(H34,Lookup!E:E,0) -> 110
D35: Major | E35: EIA - screening request sent to EST (confirm with EST when application valid) | F35: =MATCH(E35,Lookup!D:D,0) -> 110 | G35: Non-major | H35: EIA outcome (publish any letter to gov.uk) | I35: =MATCH(H35,Lookup!E:E,0) -> 111
D36: Major | E36: EIA outcome (publish any letter to gov.uk) | F36: =MATCH(E36,Lookup!D:D,0) -> 111 | G36: Non-major | H36: Consultations sent | I36: =MATCH(H36,Lookup!E:E,0) -> 30
D37: Major | E37: Consultations sent | F37: =MATCH(E37,Lookup!D:D,0) -> 30 | G37: Non-major | H37: Consultations deadline (see Statutory Consultees and Town Parish Council list for list of parties consulted) | I37: =MATCH(H37,Lookup!E:E,0) -> 31
D38: Major | E38: Consultations deadline (see Statutory Consultees and Town Parish Council list for list of parties consulted) | F38: =MATCH(E38,Lookup!D:D,0) -> 31 | G38: Non-major | H38: LPA Interested parties notification date | I38: =MATCH(H38,Lookup!E:E,0) -> 23
D39: Major | E39: LPA Interested parties notification date | F39: =MATCH(E39,Lookup!D:D,0) -> 23 | G39: Non-major | H39: LPA Interested parties deadline | I39: =MATCH(H39,Lookup!E:E,0) -> 25
D40: Major | E40: LPA Interested parties deadline | F40: =MATCH(E40,Lookup!D:D,0) -> 25 | G40: Non-major | H40: PINS Interested parties press notice placed and TMP ref | I40: =MATCH(H40,Lookup!E:E,0) -> 22
... D58: Major | E58: Grant/Refuse | F58: =MATCH(E58,Lookup!D:D,0) -> 138 | G58: Non-major | H58: Comments/Notes | I58: =MATCH(H58,Lookup!E:E,0) -> 142
D59: Major | E59: Time taken from valid to decision | F59: =MATCH(E59,Lookup!D:D,0) -> 195
D60: Major | E60: Comments/Notes | F60: =MATCH(E60,Lookup!D:D,0) -> 142
